classad/__init__.py
classad/_base_expression.py
classad/_expression.py
classad/_functions.py
classad/_grammar.py
classad/_operator.py
classad/_primitives.py
classad-0.4.1.dist-info/LICENSE
classad-0.4.1.dist-info/WHEEL
classad-0.4.1.dist-info/METADATA
classad-0.4.1.dist-info/RECORD
