Metadata-Version: 2.1
Name: classad
Version: 0.4.1
Summary: Python package to parse and interpret HTCondor classads
Home-page: https://github.com/MaineKuehn/classad
License: UNKNOWN
Keywords: htcondor classad python
Author: Eileen Kuehn, Max Fischer
Author-email: mainekuehn@gmail.com
Classifier: License :: OSI Approved :: MIT License
Requires-Dist: pyparsing ~= 2.4.2
Requires-Dist: pre-commit ; extra == "dev"
Requires-Dist: sphinx ; extra == "doc"
Requires-Dist: sphinx_rtd_theme ; extra == "doc"
Requires-Dist: sphinxcontrib-contentui ; extra == "doc"
Requires-Dist: pytest >=4.3.0 ; extra == "test"
Requires-Dist: flake8 ; extra == "test"
Requires-Dist: flake8-bugbear ; extra == "test"
Project-URL: Documentation, https://classad.readthedocs.io/en/latest/
Provides-Extra: dev
Provides-Extra: doc
Provides-Extra: test
